{
    "potential-LAMMPS": {
        "key": "1510cddb-d6fe-4100-842e-a1002a0dfe7d", 
        "id": "1987--Ackland-G-J--Ni--LAMMPS--ipr2", 
        "potential": {
            "key": "6fbc40e6-1388-4988-87d5-88805b1b3690", 
            "id": "1987--Ackland-G-J-Tichy-G-Vitek-V-Finnis-M-W--Ni"
        }, 
        "units": "metal", 
        "atom_style": "atomic", 
        "atom": {
            "element": "Ni", 
            "mass": 58.6934
        }, 
        "pair_style": {
            "type": "eam/fs"
        }, 
        "pair_coeff": {
            "term": [
                {
                    "file": "Ni_v2.eam.fs"
                }, 
                {
                    "symbols": "True"
                }
            ]
        }
    }
}