{
    "potential-LAMMPS": {
        "key": "1beb611f-e2ea-4404-961d-0dbfe58ebaac", 
        "id": "2012--Mendelev-M-I--Ni-Zr--LAMMPS--ipr1", 
        "potential": {
            "key": "2d5b5a05-a57f-4986-95ea-c5940c51d4d7", 
            "id": "2012--Mendelev-M-I-Kramer-M-J-Hao-S-G-et-al--Ni-Zr"
        }, 
        "units": "metal", 
        "atom_style": "atomic", 
        "atom": [
            {
                "element": "Ni", 
                "mass": 58.6934
            }, 
            {
                "element": "Zr", 
                "mass": 91.224
            }
        ], 
        "pair_style": {
            "type": "eam/fs"
        }, 
        "pair_coeff": {
            "term": [
                {
                    "file": "Ni-Zr_Mendelev_2012.eam.fs"
                }, 
                {
                    "symbols": "True"
                }
            ]
        }
    }
}