{
    "potential-LAMMPS": {
        "key": "e23e9eec-887b-4cd4-84db-642bc81467ea", 
        "id": "2016--Nichol-A--Rb--LAMMPS--ipr1", 
        "status": "superseded", 
        "potential": {
            "key": "d29d05b2-33eb-402e-98b2-3e52c8d3db9a", 
            "id": "2016--Nichol-A-Ackland-G-J--Rb"
        }, 
        "units": "metal", 
        "atom_style": "atomic", 
        "atom": {
            "element": "Rb", 
            "mass": 85.46
        }, 
        "pair_style": {
            "type": "eam/fs"
        }, 
        "pair_coeff": {
            "term": [
                {
                    "file": "Rb.eam.fs"
                }, 
                {
                    "symbols": "True"
                }
            ]
        }
    }
}