{
    "potential-LAMMPS": {
        "key": "f4fb9bd7-3199-4861-9a05-6f2e9013b63e", 
        "id": "2017--Zhou-X-W--In-Ga-N--LAMMPS--ipr1", 
        "potential": {
            "key": "f4c3e281-bafc-4d23-9571-a796d8b1053f", 
            "id": "2017--Zhou-X-W-Jones-R-E-Chu-K--In-Ga-N"
        }, 
        "units": "metal", 
        "atom_style": "atomic", 
        "allsymbols": "True",
        "atom": [
            {
                "element": "In", 
                "mass": 114.82
            }, 
            {
                "element": "Ga", 
                "mass": 69.723
            }, 
            {
                "element": "N", 
                "mass": 14.007
            }
        ], 
        "pair_style": {
            "type": "polymorphic"
        }, 
        "pair_coeff": {
            "term": [
                {
                    "file": "InGaN.psw"
                }, 
                {
                    "symbols": "True"
                }
            ]
        }
    }
}