{
    "potential-LAMMPS": {
        "key": "c0aa8f35-ddfc-48aa-8737-655dacc46e95", 
        "id": "2018--Mendelev-M-I--Tb--LAMMPS--ipr1", 
        "potential": {
            "key": "ed3a1bb7-3c6c-47f6-b3ca-e05870435610", 
            "id": "2018--Mendelev-M-I-Zhang-F-Song-H-et-al--Tb"
        }, 
        "units": "metal", 
        "atom_style": "atomic", 
        "atom": {
            "element": "Tb", 
            "mass": 158.92534
        }, 
        "pair_style": {
            "type": "eam/fs"
        }, 
        "pair_coeff": {
            "term": [
                {
                    "file": "Tb.eam.fs"
                }, 
                {
                    "symbols": "True"
                }
            ]
        }
    }
}