{
    "interatomic-potential-implementation": {
        "key": "66f07016-7751-4d29-9b05-a33598eb26f8", 
        "id": "2016--Nichol-A--Na--MOLDY--ipr1", 
        "status": "active", 
        "date": "2009-06-30", 
        "interatomic-potential-key": "d3ec6aef-1fc5-4151-a290-6e61acd25a77", 
        "type": "Moldy FS", 
        "notes": {
            "text": "The parameters in Na.moldy were obtained from <a href=\"http://homepages.ed.ac.uk/graeme/moldy/moldy.html\" class=\"external\">http://homepages.ed.ac.uk/graeme/moldy/moldy.html </a> and posted with the permission of G.J. Ackland."
        }, 
        "artifact": {
            "web-link": {
                "URL": "https://www.ctcms.nist.gov/potentials/Download/2016--Nichol-A-Ackland-G-J--Na/1/Na.moldy", 
                "link-text": "Na.moldy"
            }
        }
    }
}